auto_economics/__init__.py
auto_economics/_modidx.py
auto_economics/core.py
auto_economics-0.0.4.dist-info/LICENSE
auto_economics-0.0.4.dist-info/METADATA
auto_economics-0.0.4.dist-info/WHEEL
auto_economics-0.0.4.dist-info/entry_points.txt
auto_economics-0.0.4.dist-info/top_level.txt
auto_economics-0.0.4.dist-info/RECORD
